LICENSE
MANIFEST.in
README.md
setup.cfg
setup.py
proc_plot/__init__.py
proc_plot/pp.py
proc_plot.egg-info/PKG-INFO
proc_plot.egg-info/SOURCES.txt
proc_plot.egg-info/dependency_links.txt
proc_plot.egg-info/requires.txt
proc_plot.egg-info/top_level.txt