Metadata-Version: 2.1
Name: proc-plot
Version: 1.5
Summary: Trending for Process Control Data Analysis
Home-page: https://github.com/fpieterse/proc_plot
Author: Francois Pieterse
Author-email: francois.pieterse@greenferndynamics.com
License: GPLv3
Download-URL: https://github.com/fpieterse/proc_plot/archive/v1.5.tar.gz
Keywords: Trend,Process Control
Platform: UNKNOWN
Classifier: Development Status :: 5 - Production/Stable
Classifier: Intended Audience :: Manufacturing
Classifier: License :: OSI Approved :: GNU General Public License v3 or later (GPLv3+)
Classifier: Programming Language :: Python :: 3
Classifier: Programming Language :: Python :: 3.6
Classifier: Programming Language :: Python :: 3.7
Classifier: Programming Language :: Python :: 3.8
